qwer_replayPulse/main.py
qwer_replayPulse/player.py
qwer_replayPulse/recorder.py
qwer_replayPulse/settings.py
qwer_replaypulse-2.0.0.dist-info/METADATA
qwer_replaypulse-2.0.0.dist-info/WHEEL
qwer_replaypulse-2.0.0.dist-info/entry_points.txt
qwer_replaypulse-2.0.0.dist-info/top_level.txt
qwer_replaypulse-2.0.0.dist-info/RECORD
